{"PictureUri":"https://area23.at/schnapsen/cardpics/","PictureUrl":"https://area23.at/schnapsen/cardpics/","PrefixUrl":"https://area23.at/schnapsen/cardpics/","PrefixUri":"https://area23.at/schnapsen/cardpics/","Locale":"de-DE","SystemLLocale":"de-DE","LocaleString":"German (Germany)","TwoLetterISOLanguageName":"de","Game":null,"Tournement":{"tHistory":["7, 7"],"GamblerTPoints":7,"ComputerTPoints":7,"NextGameGiver":2,"NextGameStarter":1,"WonTournement":0,"Taylor":false},"CardEmpty":{"isAtou":false,"isValidCard":false,"FullName":"EMPTY","CardColor":101,"CardValue":-2,"ColorValue":"e-2"},"CardNone":{"isAtou":false,"isValidCard":false,"FullName":"NONE","CardColor":110,"CardValue":-1,"ColorValue":"n-1"}}